CHANGES.txt
LICENSE.txt
MANIFEST.in
README.txt
setup.py
src/p01/__init__.py
src/p01.statsd.egg-info/PKG-INFO
src/p01.statsd.egg-info/SOURCES.txt
src/p01.statsd.egg-info/dependency_links.txt
src/p01.statsd.egg-info/entry_points.txt
src/p01.statsd.egg-info/namespace_packages.txt
src/p01.statsd.egg-info/not-zip-safe
src/p01.statsd.egg-info/requires.txt
src/p01.statsd.egg-info/top_level.txt
src/p01/statsd/README.txt
src/p01/statsd/__init__.py
src/p01/statsd/backend.py
src/p01/statsd/client.py
src/p01/statsd/scripts.py
src/p01/statsd/server.py
src/p01/statsd/tests/__init__.py
src/p01/statsd/tests/checker.txt
src/p01/statsd/tests/test_client.py
src/p01/statsd/tests/test_docs.py
src/p01/statsd/tests/test_server.py