Metadata-Version: 1.1
Name: p01.statsd
Version: 0.5.0
Summary: Statsd client and server implementation
Home-page: http://pypi.python.org/pypi/p01.statsd
Author: Roger Ineichen, Projekt01 GmbH
Author-email: dev@projekt01.ch
License: ZPL 2.1
Keywords: Zope3 z3c p01 statsd pickle graphite
Platform: UNKNOWN
Classifier: Development Status :: 5 - Production/Stable
Classifier: Environment :: Web Environment
Classifier: Intended Audience :: Developers
Classifier: License :: OSI Approved :: Zope Public License
Classifier: Programming Language :: Python
Classifier: Natural Language :: English
Classifier: Operating System :: OS Independent
Classifier: Topic :: Internet :: WWW/HTTP
Classifier: Framework :: Zope3
